Workbook

Sheet Read Me
A1: Wedding Budget & Vendor Payment Tracker
A2: How to use this workbook
A4: 1. Go to the 'Budget Overview' tab. Set your total wedding budget in the yellow cell at
A5: the top, then edit the 'Planned Budget' column (yellow) for each category.
A6: 2. Go to the 'Vendor & Payment Tracker' tab. Add one row per vendor: contract total,
A7: deposit amount, due dates, and paid status. Match the Category column exactly to a
A8: category name from Budget Overview so the totals roll up correctly.
A9: 3. The 'Actual Spent' and 'Difference' columns on Budget Overview update automatically —
A10: they sum every vendor row tagged with that category. Nothing there needs editing.
A11: 4. 'Balance Due' on the Vendor tab is Contract Total minus Deposit Amount — a live formula,
A12: not a typed number.
A13: 5. Replace the example rows with your own vendors; delete the examples once you no longer
... A16: This workbook is a planning tool. It does not constitute financial advice.

Sheet Budget Overview
A1: Budget Overview
A3: Total wedding budget | B3: 30000
A5: By Category
A6: Category | B6: Planned Budget | C6: Actual Spent | D6: Difference (Planned - Actual) | E6: % of Total Budget
A7: Venue & Rentals | B7: 9000 | C7: =SUMIF('Vendor & Payment Tracker'!$A$4:$A$16,A7,'Vendor & Payment Tracker'!$D$4:$D$16) | D7: =B7-C7 | E7: =B7/B3
A8: Catering & Bar | B8: 7500 | C8: =SUMIF('Vendor & Payment Tracker'!$A$4:$A$16,A8,'Vendor & Payment Tracker'!$D$4:$D$16) | D8: =B8-C8 | E8: =B8/B3
A9: Photography & Video | B9: 3000 | C9: =SUMIF('Vendor & Payment Tracker'!$A$4:$A$16,A9,'Vendor & Payment Tracker'!$D$4:$D$16) | D9: =B9-C9 | E9: =B9/B3
A10: Wedding Attire | B10: 1500 | C10: =SUMIF('Vendor & Payment Tracker'!$A$4:$A$16,A10,'Vendor & Payment Tracker'!$D$4:$D$16) | D10: =B10-C10 | E10: =B10/B3
A11: Hair & Makeup | B11: 600 | C11: =SUMIF('Vendor & Payment Tracker'!$A$4:$A$16,A11,'Vendor & Payment Tracker'!$D$4:$D$16) | D11: =B11-C11 | E11: =B11/B3
A12: Flowers & Decor | B12: 2100 | C12: =SUMIF('Vendor & Payment Tracker'!$A$4:$A$16,A12,'Vendor & Payment Tracker'!$D$4:$D$16) | D12: =B12-C12 | E12: =B12/B3
A13: Music & Entertainment | B13: 1800 | C13: =SUMIF('Vendor & Payment Tracker'!$A$4:$A$16,A13,'Vendor & Payment Tracker'!$D$4:$D$16) | D13: =B13-C13 | E13: =B13/B3
A14: Invitations & Stationery | B14: 450 | C14: =SUMIF('Vendor & Payment Tracker'!$A$4:$A$16,A14,'Vendor & Payment Tracker'!$D$4:$D$16) | D14: =B14-C14 | E14: =B14/B3
A15: Wedding Cake & Desserts | B15: 600 | C15: =SUMIF('Vendor & Payment Tracker'!$A$4:$A$16,A15,'Vendor & Payment Tracker'!$D$4:$D$16) | D15: =B15-C15 | E15: =B15/B3
A16: Transportation | B16: 450 | C16: =SUMIF('Vendor & Payment Tracker'!$A$4:$A$16,A16,'Vendor & Payment Tracker'!$D$4:$D$16) | D16: =B16-C16 | E16: =B16/B3
A17: Rings | B17: 1500 | C17: =SUMIF('Vendor & Payment Tracker'!$A$4:$A$16,A17,'Vendor & Payment Tracker'!$D$4:$D$16) | D17: =B17-C17 | E17: =B17/B3
A18: Officiant | B18: 400 | C18: =SUMIF('Vendor & Payment Tracker'!$A$4:$A$16,A18,'Vendor & Payment Tracker'!$D$4:$D$16) | D18: =B18-C18 | E18: =B18/B3
A19: Favors & Gifts | B19: 450 | C19: =SUMIF('Vendor & Payment Tracker'!$A$4:$A$16,A19,'Vendor & Payment Tracker'!$D$4:$D$16) | D19: =B19-C19 | E19: =B19/B3
A20: Miscellaneous / Buffer | B20: 650 | C20: =SUMIF('Vendor & Payment Tracker'!$A$4:$A$16,A20,'Vendor & Payment Tracker'!$D$4:$D$16) | D20: =B20-C20 | E20: =B20/B3
A21: Total | B21: =SUM(B7:B20) | C21: =SUM(C7:C20) | D21: =SUM(D7:D20) | E21: =SUM(E7:E20)
A23: Remaining vs. total budget | B23: =B3-C21

Sheet Vendor & Payment Tracker
A1: Vendor & Payment Tracker
A3: Category | B3: Vendor Name | C3: Contact | D3: Contract Total | E3: Deposit Amount | F3: Deposit Status | G3: Deposit Due | H3: Balance Due | I3: Balance Due Date | J3: Balance Paid? | K3: Notes
A4: Venue & Rentals | B4: Sunset Barn Venue | C4: booking@sunsetbarn.example | D4: 9400 | E4: 2800 | F4: Booked | G4: 3 mo before | H4: =D4-E4 | I4: See deposit due | J4: No
A5: Catering & Bar | B5: Harvest Table Catering | C5: events@harvesttable.example | D5: 7200 | E5: 2200 | F5: Booked | G5: 1 mo before | H5: =D5-E5 | I5: See deposit due | J5: No
A6: Photography & Video | B6: Golden Hour Photo Co. | C6: hello@goldenhourphoto.example | D6: 3200 | E6: 1000 | F6: Booked | G6: Day-of | H6: =D6-E6 | I6: See deposit due | J6: No
A7: Wedding Attire | B7: Bridal Boutique + Men's Wearhouse | C7: - | D7: 1450 | E7: 1450 | F7: Paid in full | G7: - | H7: =D7-E7 | I7: - | J7: Yes
A8: Hair & Makeup | B8: Glow Beauty Studio | C8: book@glowbeauty.example | D8: 600 | E8: 150 | F8: Booked | G8: Day-of | H8: =D8-E8 | I8: See deposit due | J8: No
A9: Flowers & Decor | B9: Bloom & Co Florals | C9: orders@bloomandco.example | D9: 2250 | E9: 675 | F9: Booked | G9: 2 wk before | H9: =D9-E9 | I9: See deposit due | J9: No
A10: Music & Entertainment | B10: DJ Spinlist | C10: dj@spinlist.example | D10: 1800 | E10: 500 | F10: Booked | G10: Day-of | H10: =D10-E10 | I10: See deposit due | J10: No
A11: Invitations & Stationery | B11: Paper & Pine Design | C11: studio@paperpine.example | D11: 420 | E11: 420 | F11: Paid in full | G11: - | H11: =D11-E11 | I11: - | J11: Yes
A12: Wedding Cake & Desserts | B12: Sweet Layer Bakery | C12: orders@sweetlayer.example | D12: 650 | E12: 200 | F12: Booked | G12: 1 wk before | H12: =D12-E12 | I12: See deposit due | J12: No
A13: Transportation | B13: Classic Car Rentals | C13: rentals@classiccars.example | D13: 400 | E13: 100 | F13: Booked | G13: Day-of | H13: =D13-E13 | I13: See deposit due | J13: No
A14: Rings | B14: Heirloom Jewelers | C14: sales@heirloomjewelers.example | D14: 1600 | E14: 1600 | F14: Paid in full | G14: - | H14: =D14-E14 | I14: - | J14: Yes
A15: Officiant | B15: Rev. J. Alvarez | C15: j.alvarez@example.com | D15: 400 | E15: 100 | F15: Booked | G15: Day-of | H15: =D15-E15 | I15: See deposit due | J15: No
A16: Favors & Gifts | B16: Little Things Co. | C16: orders@littlethings.example | D16: 480 | E16: 480 | F16: Paid in full | G16: - | H16: =D16-E16 | I16: - | J16: Yes
A17: Total | D17: =SUM(D4:D16) | E17: =SUM(E4:E16) | H17: =SUM(H4:H16)
